<?xml version="1.0" encoding="UTF-8" ?>
<Data><Series>
  <id>290853</id>
  <Actors>|Cliff Curtis|Kim Dickens|Frank Dillane|Alycia Debnam-Carey|Michelle Ang|Colman Domingo|Patricia Reyes Spindola|Mercedes Mason|Lorenzo James Henrie|Ruben Blades|Elizabeth Rodriguez|</Actors>
  <Airs_DayOfWeek>Sunday</Airs_DayOfWeek>
  <Airs_Time>9:00 PM</Airs_Time>
  <ContentRating>TV-MA</ContentRating>
  <FirstAired>2015-08-23</FirstAired>
  <Genre>|Drama|Horror|</Genre>
  <IMDB_ID>tt3743822</IMDB_ID>
  <Language>en</Language>
  <Network>AMC</Network>
  <NetworkID></NetworkID>
  <Overview>A horrifying zombiocalypse spin-off series from The Walking Dead, set in the same universe but starting at a far earlier time in Los Angeles. The show follows normal people learning to deal with the rapidly growing collapse of civilization, at the very beginning of a zombie outbreak.

In Los Angeles, a city where people come to escape, shield secrets, and bury their pasts, we follow this mysterious outbreak as it threatens to disrupt what little stability high school guidance counselor Madison Clark and English teacher Travis Manawa have managed to assemble. 

The pressure of blending two families while dealing with resentful, escapist, and strung out children takes a back seat when society begins to break down. A forced evolution, and survival of the fittest takes hold, as our dysfunctional family finds they must either reinvent themselves or embrace their darker histories.</Overview>
  <Rating>8.2</Rating>
  <RatingCount>106</RatingCount>
  <Runtime>45</Runtime>
  <SeriesID>195810</SeriesID>
  <SeriesName>Fear the Walking Dead</SeriesName>
  <Status>Continuing</Status>
  <added>2015-01-17 09:19:59</added>
  <addedBy>421413</addedBy>
  <banner>graphical/290853-g6.jpg</banner>
  <fanart>fanart/original/290853-20.jpg</fanart>
  <lastupdated>1461760117</lastupdated>
  <poster>posters/290853-8.jpg</poster>
  <tms_wanted_old>0</tms_wanted_old>
  <zap2it_id>EP02209982</zap2it_id>
</Series>
<Episode>
  <id>5358933</id>
  <Combined_episodenumber>1</Combined_episodenumber>
  <Combined_season>0</Combined_season>
  <DVD_chapter></DVD_chapter>
  <DVD_discid></DVD_discid>
  <DVD_episodenumber></DVD_episodenumber>
  <DVD_season></DVD_season>
  <Director>Michael McDonough</Director>
  <EpImgFlag>2</EpImgFlag>
  <EpisodeName>Flight 462: Part 1</EpisodeName>
  <EpisodeNumber>1</EpisodeNumber>
  <FirstAired>2015-10-04</FirstAired>
  <GuestStars></GuestStars>
  <IMDB_ID>tt5115444</IMDB_ID>
  <Language>en</Language>
  <Overview>A routine flight take-off is interrupted by an anxious passenger, a woman who knows more than she’s saying, and a distant scream on the other end of the phone.</Overview>
  <ProductionCode></ProductionCode>
  <Rating>6.3</Rating>
  <RatingCount>3</RatingCount>
  <SeasonNumber>0</SeasonNumber>
  <Writer>|L. Signorino|Mike Zunic|</Writer>
  <absolute_number></absolute_number>
  <airsafter_season>1</airsafter_season>
  <airsbefore_episode></airsbefore_episode>
  <airsbefore_season></airsbefore_season>
  <filename>episodes/290853/5358933.jpg</filename>
  <lastupdated>1461756816</lastupdated>
  <seasonid>610127</seasonid>
  <seriesid>290853</seriesid>
  <thumb_added>2015-10-05 07:45:54</thumb_added>
  <thumb_height>225</thumb_height>
  <thumb_width>400</thumb_width>
</Episode>
<Episode>
  <id>5359092</id>
  <Combined_episodenumber>2</Combined_episodenumber>
  <Combined_season>0</Combined_season>
  <DVD_chapter></DVD_chapter>
  <DVD_discid></DVD_discid>
  <DVD_episodenumber></DVD_episodenumber>
  <DVD_season></DVD_season>
  <Director></Director>
  <EpImgFlag>2</EpImgFlag>
  <EpisodeName>Flight 462: Part 2</EpisodeName>
  <EpisodeNumber>2</EpisodeNumber>
  <FirstAired>2015-10-11</FirstAired>
  <GuestStars></GuestStars>
  <IMDB_ID>tt5139596</IMDB_ID>
  <Language>en</Language>
  <Overview>As the plane takes off, Jake tries desperately to text his mother, while Marcus vomits into a bag as his wife tries to comfort him.</Overview>
  <ProductionCode></ProductionCode>
  <Rating>6.8</Rating>
  <RatingCount>4</RatingCount>
  <SeasonNumber>0</SeasonNumber>
  <Writer></Writer>
  <absolute_number></absolute_number>
  <airsafter_season>1</airsafter_season>
  <airsbefore_episode></airsbefore_episode>
  <airsbefore_season></airsbefore_season>
  <filename>episodes/290853/5359092.jpg</filename>
  <lastupdated>1461756833</lastupdated>
  <seasonid>610127</seasonid>
  <seriesid>290853</seriesid>
  <thumb_added>2015-10-19 09:17:19</thumb_added>
  <thumb_height>225</thumb_height>
  <thumb_width>400</thumb_width>
</Episode>
<Episode>
  <id>5359093</id>
  <Combined_episodenumber>3</Combined_episodenumber>
  <Combined_season>0</Combined_season>
  <DVD_chapter></DVD_chapter>
  <DVD_discid></DVD_discid>
  <DVD_episodenumber></DVD_episodenumber>
  <DVD_season></DVD_season>
  <Director></Director>
  <EpImgFlag>2</EpImgFlag>
  <EpisodeName>Flight 462: Part 3</EpisodeName>
  <EpisodeNumber>3</EpisodeNumber>
  <FirstAired>2015-10-18</FirstAired>
  <GuestStars></GuestStars>
  <IMDB_ID>tt5139606</IMDB_ID>
  <Language>en</Language>
  <Overview>The flight attendants begin to serve drinks throughout the cabin, and Jake has a short discussion with Connie about how he ended up on the plane without his mother.</Overview>
  <ProductionCode></ProductionCode>
  <Rating>6.8</Rating>
  <RatingCount>4</RatingCount>
  <SeasonNumber>0</SeasonNumber>
  <Writer></Writer>
  <absolute_number></absolute_number>
  <airsafter_season>1</airsafter_season>
  <airsbefore_episode></airsbefore_episode>
  <airsbefore_season></airsbefore_season>
  <filename>episodes/290853/5359093.jpg</filename>
  <lastupdated>1461756845</lastupdated>
  <seasonid>610127</seasonid>
  <seriesid>290853</seriesid>
  <thumb_added>2015-10-27 13:28:04</thumb_added>
  <thumb_height>225</thumb_height>
  <thumb_width>400</thumb_width>
</Episode>
<Episode>
  <id>5359094</id>
  <Combined_episodenumber>4</Combined_episodenumber>
  <Combined_season>0</Combined_season>
  <DVD_chapter></DVD_chapter>
  <DVD_discid></DVD_discid>
  <DVD_episodenumber></DVD_episodenumber>
  <DVD_season></DVD_season>
  <Director></Director>
  <EpImgFlag>2</EpImgFlag>
  <EpisodeName>Flight 462: Part 4</EpisodeName>
  <EpisodeNumber>4</EpisodeNumber>
  <FirstAired>2015-10-25</FirstAired>
  <GuestStars></GuestStars>
  <IMDB_ID>tt5068132</IMDB_ID>
  <Language>en</Language>
  <Overview>A man on board starts to feel sick and urgently has to use the lavatory. His wife claims, he suffers from reflux.</Overview>
  <ProductionCode></ProductionCode>
  <Rating>6.3</Rating>
  <RatingCount>3</RatingCount>
  <SeasonNumber>0</SeasonNumber>
  <Writer></Writer>
  <absolute_number></absolute_number>
  <airsafter_season>1</airsafter_season>
  <airsbefore_episode></airsbefore_episode>
  <airsbefore_season></airsbefore_season>
  <filename>episodes/290853/5359094.jpg</filename>
  <lastupdated>1461756855</lastupdated>
  <seasonid>610127</seasonid>
  <seriesid>290853</seriesid>
  <thumb_added>2015-11-06 21:53:07</thumb_added>
  <thumb_height>225</thumb_height>
  <thumb_width>400</thumb_width>
</Episode>
<Episode>
  <id>5359095</id>
  <Combined_episodenumber>5</Combined_episodenumber>
  <Combined_season>0</Combined_season>
  <DVD_chapter></DVD_chapter>
  <DVD_discid></DVD_discid>
  <DVD_episodenumber></DVD_episodenumber>
  <DVD_season></DVD_season>
  <Director></Director>
  <EpImgFlag>2</EpImgFlag>
  <EpisodeName>Flight 462: Part 5</EpisodeName>
  <EpisodeNumber>5</EpisodeNumber>
  <FirstAired>2015-11-01</FirstAired>
  <GuestStars></GuestStars>
  <IMDB_ID>tt5068138</IMDB_ID>
  <Language>en</Language>
  <Overview>The passengers are asked to prepare for the descent to Phoenix.</Overview>
  <ProductionCode></ProductionCode>
  <Rating>6.7</Rating>
  <RatingCount>3</RatingCount>
  <SeasonNumber>0</SeasonNumber>
  <Writer></Writer>
  <absolute_number></absolute_number>
  <airsafter_season>1</airsafter_season>
  <airsbefore_episode></airsbefore_episode>
  <airsbefore_season></airsbefore_season>
  <filename>episodes/290853/5359095.jpg</filename>
  <lastupdated>1461756864</lastupdated>
  <seasonid>610127</seasonid>
  <seriesid>290853</seriesid>
  <thumb_added>2015-11-06 22:18:28</thumb_added>
  <thumb_height>225</thumb_height>
  <thumb_width>400</thumb_width>
</Episode>
<Episode>
  <id>5396714</id>
  <Combined_episodenumber>6</Combined_episodenumber>
  <Combined_season>0</Combined_season>
  <DVD_chapter></DVD_chapter>
  <DVD_discid></DVD_discid>
  <DVD_episodenumber></DVD_episodenumber>
  <DVD_season></DVD_season>
  <Director></Director>
  <EpImgFlag>2</EpImgFlag>
  <EpisodeName>Flight 462: Part 6</EpisodeName>
  <EpisodeNumber>6</EpisodeNumber>
  <FirstAired>2015-11-08</FirstAired>
  <GuestStars></GuestStars>
  <IMDB_ID>tt5068158</IMDB_ID>
  <Language>en</Language>
  <Overview>As a blackout continues to roll across Phoenix, Charlie urges Deirdre not to open the door. Suddenly, the bathroom door opens and Marcus falls out, unconscious.</Overview>
  <ProductionCode></ProductionCode>
  <Rating>7.0</Rating>
  <RatingCount>3</RatingCount>
  <SeasonNumber>0</SeasonNumber>
  <Writer></Writer>
  <absolute_number></absolute_number>
  <airsafter_season>1</airsafter_season>
  <airsbefore_episode></airsbefore_episode>
  <airsbefore_season></airsbefore_season>
  <filename>episodes/290853/5396714.jpg</filename>
  <lastupdated>1461756881</lastupdated>
  <seasonid>610127</seasonid>
  <seriesid>290853</seriesid>
  <thumb_added>2015-11-17 02:17:17</thumb_added>
  <thumb_height>225</thumb_height>
  <thumb_width>400</thumb_width>
</Episode>
<Episode>
  <id>5402951</id>
  <Combined_episodenumber>7</Combined_episodenumber>
  <Combined_season>0</Combined_season>
  <DVD_chapter></DVD_chapter>
  <DVD_discid></DVD_discid>
  <DVD_episodenumber></DVD_episodenumber>
  <DVD_season></DVD_season>
  <Director></Director>
  <EpImgFlag>2</EpImgFlag>
  <EpisodeName>Flight 462: Part 7</EpisodeName>
  <EpisodeNumber>7</EpisodeNumber>
  <FirstAired>2015-11-15</FirstAired>
  <GuestStars></GuestStars>
  <IMDB_ID>tt5068160</IMDB_ID>
  <Language>en</Language>
  <Overview>The passengers learn what they're up against as the plane re-routes from Phoenix to Los Angeles.</Overview>
  <ProductionCode></ProductionCode>
  <Rating>6.5</Rating>
  <RatingCount>2</RatingCount>
  <SeasonNumber>0</SeasonNumber>
  <Writer></Writer>
  <absolute_number></absolute_number>
  <airsafter_season>1</airsafter_season>
  <airsbefore_episode></airsbefore_episode>
  <airsbefore_season></airsbefore_season>
  <filename>episodes/290853/5402951.jpg</filename>
  <lastupdated>1461756896</lastupdated>
  <seasonid>610127</seasonid>
  <seriesid>290853</seriesid>
  <thumb_added>2015-11-17 02:16:26</thumb_added>
  <thumb_height>225</thumb_height>
  <thumb_width>400</thumb_width>
</Episode>
<Episode>
  <id>5411535</id>
  <Combined_episodenumber>8</Combined_episodenumber>
  <Combined_season>0</Combined_season>
  <DVD_chapter></DVD_chapter>
  <DVD_discid></DVD_discid>
  <DVD_episodenumber></DVD_episodenumber>
  <DVD_season></DVD_season>
  <Director></Director>
  <EpImgFlag>2</EpImgFlag>
  <EpisodeName>Flight 462: Part 8</EpisodeName>
  <EpisodeNumber>8</EpisodeNumber>
  <FirstAired>2015-11-22</FirstAired>
  <GuestStars></GuestStars>
  <IMDB_ID></IMDB_ID>
  <Language>en</Language>
  <Overview>Anthony, an U.S. Air Marshal demands that all the passengers return to their seats, despite Charlie's warning that Marcus is now dangerous.</Overview>
  <ProductionCode></ProductionCode>
  <Rating>6.0</Rating>
  <RatingCount>2</RatingCount>
  <SeasonNumber>0</SeasonNumber>
  <Writer></Writer>
  <absolute_number></absolute_number>
  <airsafter_season>1</airsafter_season>
  <airsbefore_episode></airsbefore_episode>
  <airsbefore_season></airsbefore_season>
  <filename>episodes/290853/5411535.jpg</filename>
  <lastupdated>1461756905</lastupdated>
  <seasonid>610127</seasonid>
  <seriesid>290853</seriesid>
  <thumb_added>2015-11-27 09:29:43</thumb_added>
  <thumb_height>225</thumb_height>
  <thumb_width>400</thumb_width>
</Episode>
<Episode>
  <id>5455475</id>
  <Combined_episodenumber>9</Combined_episodenumber>
  <Combined_season>0</Combined_season>
  <DVD_chapter></DVD_chapter>
  <DVD_discid></DVD_discid>
  <DVD_episodenumber></DVD_episodenumber>
  <DVD_season></DVD_season>
  <Director></Director>
  <EpImgFlag></EpImgFlag>
  <EpisodeName>Greeting from Set</EpisodeName>
  <EpisodeNumber>9</EpisodeNumber>
  <FirstAired>2015-07-06</FirstAired>
  <GuestStars></GuestStars>
  <IMDB_ID></IMDB_ID>
  <Language>en</Language>
  <Overview>The cast and crew of Fear the Walking Dead welcome fans to LA and share what they’re looking forward to in the episodes to come.</Overview>
  <ProductionCode></ProductionCode>
  <Rating></Rating>
  <RatingCount>0</RatingCount>
  <SeasonNumber>0</SeasonNumber>
  <Writer></Writer>
  <absolute_number></absolute_number>
  <airsafter_season></airsafter_season>
  <airsbefore_episode></airsbefore_episode>
  <airsbefore_season></airsbefore_season>
  <filename></filename>
  <lastupdated>1461756915</lastupdated>
  <seasonid>610127</seasonid>
  <seriesid>290853</seriesid>
  <thumb_added></thumb_added>
  <thumb_height></thumb_height>
  <thumb_width></thumb_width>
</Episode>
<Episode>
  <id>5455476</id>
  <Combined_episodenumber>10</Combined_episodenumber>
  <Combined_season>0</Combined_season>
  <DVD_chapter></DVD_chapter>
  <DVD_discid></DVD_discid>
  <DVD_episodenumber></DVD_episodenumber>
  <DVD_season></DVD_season>
  <Director></Director>
  <EpImgFlag></EpImgFlag>
  <EpisodeName>Fear the Walking Dead: A Look at the Series</EpisodeName>
  <EpisodeNumber>10</EpisodeNumber>
  <FirstAired>2015-08-17</FirstAired>
  <GuestStars></GuestStars>
  <IMDB_ID></IMDB_ID>
  <Language>en</Language>
  <Overview>Go behind the scenes with the cast and crew and find out what to expect from Fear the Walking Dead.</Overview>
  <ProductionCode></ProductionCode>
  <Rating></Rating>
  <RatingCount>0</RatingCount>
  <SeasonNumber>0</SeasonNumber>
  <Writer></Writer>
  <absolute_number></absolute_number>
  <airsafter_season></airsafter_season>
  <airsbefore_episode></airsbefore_episode>
  <airsbefore_season></airsbefore_season>
  <filename></filename>
  <lastupdated>1461756925</lastupdated>
  <seasonid>610127</seasonid>
  <seriesid>290853</seriesid>
  <thumb_added></thumb_added>
  <thumb_height></thumb_height>
  <thumb_width></thumb_width>
</Episode>
<Episode>
  <id>5455477</id>
  <Combined_episodenumber>11</Combined_episodenumber>
  <Combined_season>0</Combined_season>
  <DVD_chapter></DVD_chapter>
  <DVD_discid></DVD_discid>
  <DVD_episodenumber></DVD_episodenumber>
  <DVD_season></DVD_season>
  <Director></Director>
  <EpImgFlag></EpImgFlag>
  <EpisodeName>Inside Fear the Walking Dead: Episode 101, “Pilot”</EpisodeName>
  <EpisodeNumber>11</EpisodeNumber>
  <FirstAired>2015-08-24</FirstAired>
  <GuestStars></GuestStars>
  <IMDB_ID></IMDB_ID>
  <Language>en</Language>
  <Overview>The cast and creators take a deeper look at the world of Madison Clark, Travis Manawa and their families, whose lives are disrupted by an unknown virus.</Overview>
  <ProductionCode></ProductionCode>
  <Rating></Rating>
  <RatingCount>0</RatingCount>
  <SeasonNumber>0</SeasonNumber>
  <Writer></Writer>
  <absolute_number></absolute_number>
  <airsafter_season></airsafter_season>
  <airsbefore_episode></airsbefore_episode>
  <airsbefore_season></airsbefore_season>
  <filename></filename>
  <lastupdated>1461756932</lastupdated>
  <seasonid>610127</seasonid>
  <seriesid>290853</seriesid>
  <thumb_added></thumb_added>
  <thumb_height></thumb_height>
  <thumb_width></thumb_width>
</Episode>
<Episode>
  <id>5455515</id>
  <Combined_episodenumber>12</Combined_episodenumber>
  <Combined_season>0</Combined_season>
  <DVD_chapter></DVD_chapter>
  <DVD_discid></DVD_discid>
  <DVD_episodenumber></DVD_episodenumber>
  <DVD_season></DVD_season>
  <Director></Director>
  <EpImgFlag></EpImgFlag>
  <EpisodeName>Inside Fear the Walking Dead: Episode 102, “So Close, Yet So Far”</EpisodeName>
  <EpisodeNumber>12</EpisodeNumber>
  <FirstAired>2015-08-31</FirstAired>
  <GuestStars></GuestStars>
  <IMDB_ID></IMDB_ID>
  <Language>en</Language>
  <Overview>Madison and Travis are separated in the midst of the growing chaos. Travis and Liza discover the compassion of strangers when they meet the Salazar family.</Overview>
  <ProductionCode></ProductionCode>
  <Rating></Rating>
  <RatingCount>0</RatingCount>
  <SeasonNumber>0</SeasonNumber>
  <Writer></Writer>
  <absolute_number></absolute_number>
  <airsafter_season></airsafter_season>
  <airsbefore_episode></airsbefore_episode>
  <airsbefore_season></airsbefore_season>
  <filename></filename>
  <lastupdated>1461756942</lastupdated>
  <seasonid>610127</seasonid>
  <seriesid>290853</seriesid>
  <thumb_added></thumb_added>
  <thumb_height></thumb_height>
  <thumb_width></thumb_width>
</Episode>
<Episode>
  <id>5455516</id>
  <Combined_episodenumber>13</Combined_episodenumber>
  <Combined_season>0</Combined_season>
  <DVD_chapter></DVD_chapter>
  <DVD_discid></DVD_discid>
  <DVD_episodenumber></DVD_episodenumber>
  <DVD_season></DVD_season>
  <Director></Director>
  <EpImgFlag></EpImgFlag>
  <EpisodeName>Inside Fear the Walking Dead: Episode 103, “The Dog”</EpisodeName>
  <EpisodeNumber>13</EpisodeNumber>
  <FirstAired>2015-09-14</FirstAired>
  <GuestStars></GuestStars>
  <IMDB_ID></IMDB_ID>
  <Language>en</Language>
  <Overview>The Manawa, Salazar and Clark families band together for safety as the deadly effects of the virus hit closer to home.</Overview>
  <ProductionCode></ProductionCode>
  <Rating></Rating>
  <RatingCount>0</RatingCount>
  <SeasonNumber>0</SeasonNumber>
  <Writer></Writer>
  <absolute_number></absolute_number>
  <airsafter_season></airsafter_season>
  <airsbefore_episode></airsbefore_episode>
  <airsbefore_season></airsbefore_season>
  <filename></filename>
  <lastupdated>1461756952</lastupdated>
  <seasonid>610127</seasonid>
  <seriesid>290853</seriesid>
  <thumb_added></thumb_added>
  <thumb_height></thumb_height>
  <thumb_width></thumb_width>
</Episode>
<Episode>
  <id>5455517</id>
  <Combined_episodenumber>14</Combined_episodenumber>
  <Combined_season>0</Combined_season>
  <DVD_chapter></DVD_chapter>
  <DVD_discid></DVD_discid>
  <DVD_episodenumber></DVD_episodenumber>
  <DVD_season></DVD_season>
  <Director></Director>
  <EpImgFlag></EpImgFlag>
  <EpisodeName>Inside Fear the Walking Dead: Episode 104, “Not Fade Away”</EpisodeName>
  <EpisodeNumber>14</EpisodeNumber>
  <FirstAired>2015-09-21</FirstAired>
  <GuestStars></GuestStars>
  <IMDB_ID></IMDB_ID>
  <Language>en</Language>
  <Overview>Tensions rise among the group during the military occupation, as they begin to realize that the soldiers are not their allies.</Overview>
  <ProductionCode></ProductionCode>
  <Rating></Rating>
  <RatingCount>0</RatingCount>
  <SeasonNumber>0</SeasonNumber>
  <Writer></Writer>
  <absolute_number></absolute_number>
  <airsafter_season></airsafter_season>
  <airsbefore_episode></airsbefore_episode>
  <airsbefore_season></airsbefore_season>
  <filename></filename>
  <lastupdated>1461756960</lastupdated>
  <seasonid>610127</seasonid>
  <seriesid>290853</seriesid>
  <thumb_added></thumb_added>
  <thumb_height></thumb_height>
  <thumb_width></thumb_width>
</Episode>
<Episode>
  <id>5455518</id>
  <Combined_episodenumber>15</Combined_episodenumber>
  <Combined_season>0</Combined_season>
  <DVD_chapter></DVD_chapter>
  <DVD_discid></DVD_discid>
  <DVD_episodenumber></DVD_episodenumber>
  <DVD_season></DVD_season>
  <Director></Director>
  <EpImgFlag></EpImgFlag>
  <EpisodeName>Inside Fear the Walking Dead: Episode 105, “Cobalt”</EpisodeName>
  <EpisodeNumber>15</EpisodeNumber>
  <FirstAired>2015-09-28</FirstAired>
  <GuestStars></GuestStars>
  <IMDB_ID></IMDB_ID>
  <Language>en</Language>
  <Overview>Daniel and Madison resort to dubious measures to get information from the military and keep their families safe.</Overview>
  <ProductionCode></ProductionCode>
  <Rating></Rating>
  <RatingCount>0</RatingCount>
  <SeasonNumber>0</SeasonNumber>
  <Writer></Writer>
  <absolute_number></absolute_number>
  <airsafter_season></airsafter_season>
  <airsbefore_episode></airsbefore_episode>
  <airsbefore_season></airsbefore_season>
  <filename></filename>
  <lastupdated>1461756970</lastupdated>
  <seasonid>610127</seasonid>
  <seriesid>290853</seriesid>
  <thumb_added></thumb_added>
  <thumb_height></thumb_height>
  <thumb_width></thumb_width>
</Episode>
<Episode>
  <id>5455519</id>
  <Combined_episodenumber>16</Combined_episodenumber>
  <Combined_season>0</Combined_season>
  <DVD_chapter></DVD_chapter>
  <DVD_discid></DVD_discid>
  <DVD_episodenumber></DVD_episodenumber>
  <DVD_season></DVD_season>
  <Director></Director>
  <EpImgFlag></EpImgFlag>
  <EpisodeName>Inside Fear the Walking Dead: Episode 106, “The Good Man”</EpisodeName>
  <EpisodeNumber>16</EpisodeNumber>
  <FirstAired>2015-10-05</FirstAired>
  <GuestStars></GuestStars>
  <IMDB_ID></IMDB_ID>
  <Language>en</Language>
  <Overview>The group must contend with the realization that the world is in ruins.</Overview>
  <ProductionCode></ProductionCode>
  <Rating></Rating>
  <RatingCount>0</RatingCount>
  <SeasonNumber>0</SeasonNumber>
  <Writer></Writer>
  <absolute_number></absolute_number>
  <airsafter_season></airsafter_season>
  <airsbefore_episode></airsbefore_episode>
  <airsbefore_season></airsbefore_season>
  <filename></filename>
  <lastupdated>1461756977</lastupdated>
  <seasonid>610127</seasonid>
  <seriesid>290853</seriesid>
  <thumb_added></thumb_added>
  <thumb_height></thumb_height>
  <thumb_width></thumb_width>
</Episode>
<Episode>
  <id>5455511</id>
  <Combined_episodenumber>17</Combined_episodenumber>
  <Combined_season>0</Combined_season>
  <DVD_chapter></DVD_chapter>
  <DVD_discid></DVD_discid>
  <DVD_episodenumber></DVD_episodenumber>
  <DVD_season></DVD_season>
  <Director></Director>
  <EpImgFlag></EpImgFlag>
  <EpisodeName>A Look at Season 2: Fear the Walking Dead</EpisodeName>
  <EpisodeNumber>17</EpisodeNumber>
  <FirstAired>2015-10-04</FirstAired>
  <GuestStars></GuestStars>
  <IMDB_ID></IMDB_ID>
  <Language>en</Language>
  <Overview>The cast and creators of Fear the Walking Dead share their expectations for Season 2.</Overview>
  <ProductionCode></ProductionCode>
  <Rating></Rating>
  <RatingCount>0</RatingCount>
  <SeasonNumber>0</SeasonNumber>
  <Writer></Writer>
  <absolute_number></absolute_number>
  <airsafter_season></airsafter_season>
  <airsbefore_episode></airsbefore_episode>
  <airsbefore_season></airsbefore_season>
  <filename></filename>
  <lastupdated>1461756986</lastupdated>
  <seasonid>610127</seasonid>
  <seriesid>290853</seriesid>
  <thumb_added></thumb_added>
  <thumb_height></thumb_height>
  <thumb_width></thumb_width>
</Episode>
<Episode>
  <id>5416089</id>
  <Combined_episodenumber>18</Combined_episodenumber>
  <Combined_season>0</Combined_season>
  <DVD_chapter></DVD_chapter>
  <DVD_discid></DVD_discid>
  <DVD_episodenumber></DVD_episodenumber>
  <DVD_season></DVD_season>
  <Director></Director>
  <EpImgFlag></EpImgFlag>
  <EpisodeName>Flight 462: Part 9</EpisodeName>
  <EpisodeNumber>18</EpisodeNumber>
  <FirstAired>2016-02-14</FirstAired>
  <GuestStars></GuestStars>
  <IMDB_ID></IMDB_ID>
  <Language>en</Language>
  <Overview>A group of passengers experience the outbreak aboard a commercial plane.</Overview>
  <ProductionCode></ProductionCode>
  <Rating>5.0</Rating>
  <RatingCount>1</RatingCount>
  <SeasonNumber>0</SeasonNumber>
  <Writer></Writer>
  <absolute_number></absolute_number>
  <airsafter_season>1</airsafter_season>
  <airsbefore_episode></airsbefore_episode>
  <airsbefore_season></airsbefore_season>
  <filename></filename>
  <lastupdated>1459173005</lastupdated>
  <seasonid>610127</seasonid>
  <seriesid>290853</seriesid>
  <thumb_added></thumb_added>
  <thumb_height></thumb_height>
  <thumb_width></thumb_width>
</Episode>
<Episode>
  <id>5416090</id>
  <Combined_episodenumber>19</Combined_episodenumber>
  <Combined_season>0</Combined_season>
  <DVD_chapter></DVD_chapter>
  <DVD_discid></DVD_discid>
  <DVD_episodenumber></DVD_episodenumber>
  <DVD_season></DVD_season>
  <Director></Director>
  <EpImgFlag></EpImgFlag>
  <EpisodeName>Flight 462: Part 10</EpisodeName>
  <EpisodeNumber>19</EpisodeNumber>
  <FirstAired>2016-02-21</FirstAired>
  <GuestStars></GuestStars>
  <IMDB_ID></IMDB_ID>
  <Language>en</Language>
  <Overview></Overview>
  <ProductionCode></ProductionCode>
  <Rating>5.0</Rating>
  <RatingCount>1</RatingCount>
  <SeasonNumber>0</SeasonNumber>
  <Writer></Writer>
  <absolute_number></absolute_number>
  <airsafter_season>1</airsafter_season>
  <airsbefore_episode></airsbefore_episode>
  <airsbefore_season></airsbefore_season>
  <filename></filename>
  <lastupdated>1459173022</lastupdated>
  <seasonid>610127</seasonid>
  <seriesid>290853</seriesid>
  <thumb_added></thumb_added>
  <thumb_height></thumb_height>
  <thumb_width></thumb_width>
</Episode>
<Episode>
  <id>5416091</id>
  <Combined_episodenumber>20</Combined_episodenumber>
  <Combined_season>0</Combined_season>
  <DVD_chapter></DVD_chapter>
  <DVD_discid></DVD_discid>
  <DVD_episodenumber></DVD_episodenumber>
  <DVD_season></DVD_season>
  <Director></Director>
  <EpImgFlag></EpImgFlag>
  <EpisodeName>Flight 462: Part 11</EpisodeName>
  <EpisodeNumber>20</EpisodeNumber>
  <FirstAired>2016-02-28</FirstAired>
  <GuestStars></GuestStars>
  <IMDB_ID></IMDB_ID>
  <Language>en</Language>
  <Overview></Overview>
  <ProductionCode></ProductionCode>
  <Rating>5.0</Rating>
  <RatingCount>1</RatingCount>
  <SeasonNumber>0</SeasonNumber>
  <Writer></Writer>
  <absolute_number></absolute_number>
  <airsafter_season>1</airsafter_season>
  <airsbefore_episode></airsbefore_episode>
  <airsbefore_season></airsbefore_season>
  <filename></filename>
  <lastupdated>1459173033</lastupdated>
  <seasonid>610127</seasonid>
  <seriesid>290853</seriesid>
  <thumb_added></thumb_added>
  <thumb_height></thumb_height>
  <thumb_width></thumb_width>
</Episode>
<Episode>
  <id>5416092</id>
  <Combined_episodenumber>21</Combined_episodenumber>
  <Combined_season>0</Combined_season>
  <DVD_chapter></DVD_chapter>
  <DVD_discid></DVD_discid>
  <DVD_episodenumber></DVD_episodenumber>
  <DVD_season></DVD_season>
  <Director></Director>
  <EpImgFlag></EpImgFlag>
  <EpisodeName>Flight 462: Part 12</EpisodeName>
  <EpisodeNumber>21</EpisodeNumber>
  <FirstAired>2016-03-06</FirstAired>
  <GuestStars></GuestStars>
  <IMDB_ID></IMDB_ID>
  <Language>en</Language>
  <Overview></Overview>
  <ProductionCode></ProductionCode>
  <Rating>5.0</Rating>
  <RatingCount>1</RatingCount>
  <SeasonNumber>0</SeasonNumber>
  <Writer></Writer>
  <absolute_number></absolute_number>
  <airsafter_season>1</airsafter_season>
  <airsbefore_episode></airsbefore_episode>
  <airsbefore_season></airsbefore_season>
  <filename></filename>
  <lastupdated>1459173048</lastupdated>
  <seasonid>610127</seasonid>
  <seriesid>290853</seriesid>
  <thumb_added></thumb_added>
  <thumb_height></thumb_height>
  <thumb_width></thumb_width>
</Episode>
<Episode>
  <id>5416093</id>
  <Combined_episodenumber>22</Combined_episodenumber>
  <Combined_season>0</Combined_season>
  <DVD_chapter></DVD_chapter>
  <DVD_discid></DVD_discid>
  <DVD_episodenumber></DVD_episodenumber>
  <DVD_season></DVD_season>
  <Director></Director>
  <EpImgFlag></EpImgFlag>
  <EpisodeName>Flight 462: Part 13</EpisodeName>
  <EpisodeNumber>22</EpisodeNumber>
  <FirstAired>2016-03-13</FirstAired>
  <GuestStars></GuestStars>
  <IMDB_ID></IMDB_ID>
  <Language>en</Language>
  <Overview></Overview>
  <ProductionCode></ProductionCode>
  <Rating>5.0</Rating>
  <RatingCount>1</RatingCount>
  <SeasonNumber>0</SeasonNumber>
  <Writer></Writer>
  <absolute_number></absolute_number>
  <airsafter_season>1</airsafter_season>
  <airsbefore_episode></airsbefore_episode>
  <airsbefore_season></airsbefore_season>
  <filename></filename>
  <lastupdated>1459173060</lastupdated>
  <seasonid>610127</seasonid>
  <seriesid>290853</seriesid>
  <thumb_added></thumb_added>
  <thumb_height></thumb_height>
  <thumb_width></thumb_width>
</Episode>
<Episode>
  <id>5416094</id>
  <Combined_episodenumber>23</Combined_episodenumber>
  <Combined_season>0</Combined_season>
  <DVD_chapter></DVD_chapter>
  <DVD_discid></DVD_discid>
  <DVD_episodenumber></DVD_episodenumber>
  <DVD_season></DVD_season>
  <Director></Director>
  <EpImgFlag></EpImgFlag>
  <EpisodeName>Flight 462: Part 14</EpisodeName>
  <EpisodeNumber>23</EpisodeNumber>
  <FirstAired>2016-03-20</FirstAired>
  <GuestStars></GuestStars>
  <IMDB_ID></IMDB_ID>
  <Language>en</Language>
  <Overview></Overview>
  <ProductionCode></ProductionCode>
  <Rating>5.0</Rating>
  <RatingCount>1</RatingCount>
  <SeasonNumber>0</SeasonNumber>
  <Writer></Writer>
  <absolute_number></absolute_number>
  <airsafter_season>1</airsafter_season>
  <airsbefore_episode></airsbefore_episode>
  <airsbefore_season></airsbefore_season>
  <filename></filename>
  <lastupdated>1459173074</lastupdated>
  <seasonid>610127</seasonid>
  <seriesid>290853</seriesid>
  <thumb_added></thumb_added>
  <thumb_height></thumb_height>
  <thumb_width></thumb_width>
</Episode>
<Episode>
  <id>5416095</id>
  <Combined_episodenumber>24</Combined_episodenumber>
  <Combined_season>0</Combined_season>
  <DVD_chapter></DVD_chapter>
  <DVD_discid></DVD_discid>
  <DVD_episodenumber></DVD_episodenumber>
  <DVD_season></DVD_season>
  <Director></Director>
  <EpImgFlag></EpImgFlag>
  <EpisodeName>Flight 462: Part 15</EpisodeName>
  <EpisodeNumber>24</EpisodeNumber>
  <FirstAired>2016-03-27</FirstAired>
  <GuestStars></GuestStars>
  <IMDB_ID></IMDB_ID>
  <Language>en</Language>
  <Overview></Overview>
  <ProductionCode></ProductionCode>
  <Rating>5.0</Rating>
  <RatingCount>1</RatingCount>
  <SeasonNumber>0</SeasonNumber>
  <Writer></Writer>
  <absolute_number></absolute_number>
  <airsafter_season>1</airsafter_season>
  <airsbefore_episode></airsbefore_episode>
  <airsbefore_season></airsbefore_season>
  <filename></filename>
  <lastupdated>1459173080</lastupdated>
  <seasonid>610127</seasonid>
  <seriesid>290853</seriesid>
  <thumb_added></thumb_added>
  <thumb_height></thumb_height>
  <thumb_width></thumb_width>
</Episode>
<Episode>
  <id>5416096</id>
  <Combined_episodenumber>25</Combined_episodenumber>
  <Combined_season>0</Combined_season>
  <DVD_chapter></DVD_chapter>
  <DVD_discid></DVD_discid>
  <DVD_episodenumber></DVD_episodenumber>
  <DVD_season></DVD_season>
  <Director></Director>
  <EpImgFlag></EpImgFlag>
  <EpisodeName>Flight 462: Part 16</EpisodeName>
  <EpisodeNumber>25</EpisodeNumber>
  <FirstAired>2016-04-03</FirstAired>
  <GuestStars></GuestStars>
  <IMDB_ID></IMDB_ID>
  <Language>en</Language>
  <Overview></Overview>
  <ProductionCode></ProductionCode>
  <Rating>5.0</Rating>
  <RatingCount>1</RatingCount>
  <SeasonNumber>0</SeasonNumber>
  <Writer></Writer>
  <absolute_number></absolute_number>
  <airsafter_season>1</airsafter_season>
  <airsbefore_episode></airsbefore_episode>
  <airsbefore_season></airsbefore_season>
  <filename></filename>
  <lastupdated>1459173089</lastupdated>
  <seasonid>610127</seasonid>
  <seriesid>290853</seriesid>
  <thumb_added></thumb_added>
  <thumb_height></thumb_height>
  <thumb_width></thumb_width>
</Episode>
<Episode>
  <id>5576513</id>
  <Combined_episodenumber>26</Combined_episodenumber>
  <Combined_season>0</Combined_season>
  <DVD_chapter></DVD_chapter>
  <DVD_discid></DVD_discid>
  <DVD_episodenumber></DVD_episodenumber>
  <DVD_season></DVD_season>
  <Director></Director>
  <EpImgFlag></EpImgFlag>
  <EpisodeName>A Look Ahead</EpisodeName>
  <EpisodeNumber>26</EpisodeNumber>
  <FirstAired>2016-04-10</FirstAired>
  <GuestStars></GuestStars>
  <IMDB_ID></IMDB_ID>
  <Language>en</Language>
  <Overview>Cast and producers of &quot;Fear the Walking Dead&quot; talk about what to expect from the upcoming second season.</Overview>
  <ProductionCode></ProductionCode>
  <Rating></Rating>
  <RatingCount>0</RatingCount>
  <SeasonNumber>0</SeasonNumber>
  <Writer></Writer>
  <absolute_number></absolute_number>
  <airsafter_season></airsafter_season>
  <airsbefore_episode>1</airsbefore_episode>
  <airsbefore_season>2</airsbefore_season>
  <filename></filename>
  <lastupdated>1460216270</lastupdated>
  <seasonid>610127</seasonid>
  <seriesid>290853</seriesid>
  <thumb_added></thumb_added>
  <thumb_height></thumb_height>
  <thumb_width></thumb_width>
</Episode>
<Episode>
  <id>5578190</id>
  <Combined_episodenumber>27</Combined_episodenumber>
  <Combined_season>0</Combined_season>
  <DVD_chapter></DVD_chapter>
  <DVD_discid></DVD_discid>
  <DVD_episodenumber></DVD_episodenumber>
  <DVD_season></DVD_season>
  <Director></Director>
  <EpImgFlag>2</EpImgFlag>
  <EpisodeName>Flight 462: The Complete Story</EpisodeName>
  <EpisodeNumber>27</EpisodeNumber>
  <FirstAired>2016-04-03</FirstAired>
  <GuestStars></GuestStars>
  <IMDB_ID></IMDB_ID>
  <Language>en</Language>
  <Overview>16 webisodes following the passengers on flight 462, and how they will handle the situation when one of the passengers seems to be infected. Here, the webisodes are compiled into one single episode.</Overview>
  <ProductionCode></ProductionCode>
  <Rating>8.0</Rating>
  <RatingCount>1</RatingCount>
  <SeasonNumber>0</SeasonNumber>
  <Writer></Writer>
  <absolute_number></absolute_number>
  <airsafter_season></airsafter_season>
  <airsbefore_episode>1</airsbefore_episode>
  <airsbefore_season>2</airsbefore_season>
  <filename>episodes/290853/5578190.jpg</filename>
  <lastupdated>1460859430</lastupdated>
  <seasonid>610127</seasonid>
  <seriesid>290853</seriesid>
  <thumb_added>2016-04-11 09:21:21</thumb_added>
  <thumb_height>225</thumb_height>
  <thumb_width>400</thumb_width>
</Episode>
<Episode>
  <id>5105118</id>
  <Combined_episodenumber>1</Combined_episodenumber>
  <Combined_season>1</Combined_season>
  <DVD_chapter></DVD_chapter>
  <DVD_discid></DVD_discid>
  <DVD_episodenumber></DVD_episodenumber>
  <DVD_season></DVD_season>
  <Director>Adam Davidson</Director>
  <EpImgFlag>2</EpImgFlag>
  <EpisodeName>Pilot</EpisodeName>
  <EpisodeNumber>1</EpisodeNumber>
  <FirstAired>2015-08-23</FirstAired>
  <GuestStars></GuestStars>
  <IMDB_ID>tt4417020</IMDB_ID>
  <Language>en</Language>
  <Overview>A highly dysfunctional blended family is forced together when they realize a reported virus is actually the onset of the undead apocalypse.</Overview>
  <ProductionCode></ProductionCode>
  <Rating>7.5</Rating>
  <RatingCount>47</RatingCount>
  <SeasonNumber>1</SeasonNumber>
  <Writer>|Robert Kirkman|Dave Erickson|</Writer>
  <absolute_number>1</absolute_number>
  <filename>episodes/290853/5105118.jpg</filename>
  <lastupdated>1460305826</lastupdated>
  <seasonid>610128</seasonid>
  <seriesid>290853</seriesid>
  <thumb_added>2015-06-15 03:31:21</thumb_added>
  <thumb_height>225</thumb_height>
  <thumb_width>400</thumb_width>
</Episode>
<Episode>
  <id>5293482</id>
  <Combined_episodenumber>2</Combined_episodenumber>
  <Combined_season>1</Combined_season>
  <DVD_chapter></DVD_chapter>
  <DVD_discid></DVD_discid>
  <DVD_episodenumber></DVD_episodenumber>
  <DVD_season></DVD_season>
  <Director>Adam Davidson</Director>
  <EpImgFlag>2</EpImgFlag>
  <EpisodeName>So Close, Yet So Far</EpisodeName>
  <EpisodeNumber>2</EpisodeNumber>
  <FirstAired>2015-08-30</FirstAired>
  <GuestStars></GuestStars>
  <IMDB_ID>tt4559272</IMDB_ID>
  <Language>en</Language>
  <Overview>While Madison struggles to keep Nick from crippling withdrawal, Travis ventures out to find his son before the city of Los Angeles falls.</Overview>
  <ProductionCode></ProductionCode>
  <Rating>7.7</Rating>
  <RatingCount>44</RatingCount>
  <SeasonNumber>1</SeasonNumber>
  <Writer>Marco Ramirez</Writer>
  <absolute_number>2</absolute_number>
  <filename>episodes/290853/5293482.jpg</filename>
  <lastupdated>1460305849</lastupdated>
  <seasonid>610128</seasonid>
  <seriesid>290853</seriesid>
  <thumb_added>2015-07-31 12:58:35</thumb_added>
  <thumb_height>225</thumb_height>
  <thumb_width>400</thumb_width>
</Episode>
<Episode>
  <id>5315302</id>
  <Combined_episodenumber>3</Combined_episodenumber>
  <Combined_season>1</Combined_season>
  <DVD_chapter></DVD_chapter>
  <DVD_discid></DVD_discid>
  <DVD_episodenumber></DVD_episodenumber>
  <DVD_season></DVD_season>
  <Director>Adam Davidson</Director>
  <EpImgFlag>2</EpImgFlag>
  <EpisodeName>The Dog</EpisodeName>
  <EpisodeNumber>3</EpisodeNumber>
  <FirstAired>2015-09-13</FirstAired>
  <GuestStars></GuestStars>
  <IMDB_ID>tt4559274</IMDB_ID>
  <Language>en</Language>
  <Overview>After they escape a riot, Travis, Liza and Chris seek refuge with the Salazars. Madison defends her home.</Overview>
  <ProductionCode></ProductionCode>
  <Rating>7.8</Rating>
  <RatingCount>40</RatingCount>
  <SeasonNumber>1</SeasonNumber>
  <Writer>Jack LoGiudice</Writer>
  <absolute_number>3</absolute_number>
  <filename>episodes/290853/5315302.jpg</filename>
  <lastupdated>1460448283</lastupdated>
  <seasonid>610128</seasonid>
  <seriesid>290853</seriesid>
  <thumb_added>2015-08-31 07:47:45</thumb_added>
  <thumb_height>225</thumb_height>
  <thumb_width>400</thumb_width>
</Episode>
<Episode>
  <id>5315303</id>
  <Combined_episodenumber>4</Combined_episodenumber>
  <Combined_season>1</Combined_season>
  <DVD_chapter></DVD_chapter>
  <DVD_discid></DVD_discid>
  <DVD_episodenumber></DVD_episodenumber>
  <DVD_season></DVD_season>
  <Director>Kari Skogland</Director>
  <EpImgFlag>2</EpImgFlag>
  <EpisodeName>Not Fade Away</EpisodeName>
  <EpisodeNumber>4</EpisodeNumber>
  <FirstAired>2015-09-20</FirstAired>
  <GuestStars></GuestStars>
  <IMDB_ID>tt4559276</IMDB_ID>
  <Language>en</Language>
  <Overview>Madison and Travis see different sides of the National Guard's occupation in their neighborhood; the family tries to adapt to the new world.</Overview>
  <ProductionCode></ProductionCode>
  <Rating>7.6</Rating>
  <RatingCount>37</RatingCount>
  <SeasonNumber>1</SeasonNumber>
  <Writer>Meaghan Oppenheimer</Writer>
  <absolute_number>4</absolute_number>
  <filename>episodes/290853/5315303.jpg</filename>
  <lastupdated>1461286142</lastupdated>
  <seasonid>610128</seasonid>
  <seriesid>290853</seriesid>
  <thumb_added>2015-09-14 07:30:04</thumb_added>
  <thumb_height>225</thumb_height>
  <thumb_width>400</thumb_width>
</Episode>
<Episode>
  <id>5315304</id>
  <Combined_episodenumber>5</Combined_episodenumber>
  <Combined_season>1</Combined_season>
  <DVD_chapter></DVD_chapter>
  <DVD_discid></DVD_discid>
  <DVD_episodenumber></DVD_episodenumber>
  <DVD_season></DVD_season>
  <Director>Kari Skogland</Director>
  <EpImgFlag>2</EpImgFlag>
  <EpisodeName>Cobalt</EpisodeName>
  <EpisodeNumber>5</EpisodeNumber>
  <FirstAired>2015-09-27</FirstAired>
  <GuestStars></GuestStars>
  <IMDB_ID>tt4559278</IMDB_ID>
  <Language>en</Language>
  <Overview>The National Guard's plan for the neighborhood is revealed. Meanwhile, Travis and Madison make a difficult decision.</Overview>
  <ProductionCode></ProductionCode>
  <Rating>7.8</Rating>
  <RatingCount>33</RatingCount>
  <SeasonNumber>1</SeasonNumber>
  <Writer>David Wiener</Writer>
  <absolute_number>5</absolute_number>
  <filename>episodes/290853/5315304.jpg</filename>
  <lastupdated>1460305915</lastupdated>
  <seasonid>610128</seasonid>
  <seriesid>290853</seriesid>
  <thumb_added>2015-09-21 07:22:05</thumb_added>
  <thumb_height>225</thumb_height>
  <thumb_width>400</thumb_width>
</Episode>
<Episode>
  <id>5315305</id>
  <Combined_episodenumber>6</Combined_episodenumber>
  <Combined_season>1</Combined_season>
  <DVD_chapter></DVD_chapter>
  <DVD_discid></DVD_discid>
  <DVD_episodenumber></DVD_episodenumber>
  <DVD_season></DVD_season>
  <Director>Stefan Schwartz</Director>
  <EpImgFlag>2</EpImgFlag>
  <EpisodeName>The Good Man</EpisodeName>
  <EpisodeNumber>6</EpisodeNumber>
  <FirstAired>2015-10-04</FirstAired>
  <GuestStars>|Colman Domingo|Shawn Hatosy|Sandrine Holt|</GuestStars>
  <IMDB_ID>tt4549106</IMDB_ID>
  <Language>en</Language>
  <Overview>As civil unrest grows, and the dead take over, Travis and Madison try to devise ways to protect their families.</Overview>
  <ProductionCode></ProductionCode>
  <Rating>7.9</Rating>
  <RatingCount>32</RatingCount>
  <SeasonNumber>1</SeasonNumber>
  <Writer>|Robert Kirkman|Dave Erickson|</Writer>
  <absolute_number>6</absolute_number>
  <filename>episodes/290853/5315305.jpg</filename>
  <lastupdated>1461312091</lastupdated>
  <seasonid>610128</seasonid>
  <seriesid>290853</seriesid>
  <thumb_added>2015-09-28 07:27:06</thumb_added>
  <thumb_height>225</thumb_height>
  <thumb_width>400</thumb_width>
</Episode>
<Episode>
  <id>5470416</id>
  <Combined_episodenumber>1.0</Combined_episodenumber>
  <Combined_season>2</Combined_season>
  <DVD_chapter></DVD_chapter>
  <DVD_discid></DVD_discid>
  <DVD_episodenumber>1.0</DVD_episodenumber>
  <DVD_season>2</DVD_season>
  <Director>Adam Davidson</Director>
  <EpImgFlag>2</EpImgFlag>
  <EpisodeName>Monster</EpisodeName>
  <EpisodeNumber>1</EpisodeNumber>
  <FirstAired>2016-04-10</FirstAired>
  <GuestStars></GuestStars>
  <IMDB_ID>tt4549108</IMDB_ID>
  <Language>en</Language>
  <Overview>After fleeing a burning Los Angeles on Strand's yacht, tensions arise among the group. Strand remains mysterious. Our group encounters danger at sea.</Overview>
  <ProductionCode></ProductionCode>
  <Rating>7.6</Rating>
  <RatingCount>19</RatingCount>
  <SeasonNumber>2</SeasonNumber>
  <Writer>Dave Erickson</Writer>
  <absolute_number>7</absolute_number>
  <filename>episodes/290853/5470416.jpg</filename>
  <lastupdated>1460895191</lastupdated>
  <seasonid>651490</seasonid>
  <seriesid>290853</seriesid>
  <thumb_added>2016-01-30 09:11:30</thumb_added>
  <thumb_height>225</thumb_height>
  <thumb_width>400</thumb_width>
</Episode>
<Episode>
  <id>5555786</id>
  <Combined_episodenumber>2</Combined_episodenumber>
  <Combined_season>2</Combined_season>
  <DVD_chapter></DVD_chapter>
  <DVD_discid></DVD_discid>
  <DVD_episodenumber></DVD_episodenumber>
  <DVD_season></DVD_season>
  <Director>Adam Davidson</Director>
  <EpImgFlag>2</EpImgFlag>
  <EpisodeName>We All Fall Down</EpisodeName>
  <EpisodeNumber>2</EpisodeNumber>
  <FirstAired>2016-04-17</FirstAired>
  <GuestStars></GuestStars>
  <IMDB_ID>tt4897130</IMDB_ID>
  <Language>en</Language>
  <Overview>The group seeks shelter with a survivalist family; and Madison tries to uncover the family's true motives. Meanwhile, Salazar works to discover Strand's intentions.</Overview>
  <ProductionCode></ProductionCode>
  <Rating>7.7</Rating>
  <RatingCount>18</RatingCount>
  <SeasonNumber>2</SeasonNumber>
  <Writer>|Brett C. Leonard|Kate Barnow|</Writer>
  <absolute_number>8</absolute_number>
  <filename>episodes/290853/5555786.jpg</filename>
  <lastupdated>1461137680</lastupdated>
  <seasonid>651490</seasonid>
  <seriesid>290853</seriesid>
  <thumb_added>2016-04-10 23:55:15</thumb_added>
  <thumb_height>225</thumb_height>
  <thumb_width>400</thumb_width>
</Episode>
<Episode>
  <id>5555787</id>
  <Combined_episodenumber>3</Combined_episodenumber>
  <Combined_season>2</Combined_season>
  <DVD_chapter></DVD_chapter>
  <DVD_discid></DVD_discid>
  <DVD_episodenumber></DVD_episodenumber>
  <DVD_season></DVD_season>
  <Director>Stefan Schwartz</Director>
  <EpImgFlag>2</EpImgFlag>
  <EpisodeName>Ouroboros</EpisodeName>
  <EpisodeNumber>3</EpisodeNumber>
  <FirstAired>2016-04-24</FirstAired>
  <GuestStars></GuestStars>
  <IMDB_ID>tt5218334</IMDB_ID>
  <Language>en</Language>
  <Overview>Madison confronts Strand about his mysterious destination. Meanwhile, Nick, Alicia and others inspect wreckage from a plane crash.</Overview>
  <ProductionCode></ProductionCode>
  <Rating>7.3</Rating>
  <RatingCount>14</RatingCount>
  <SeasonNumber>2</SeasonNumber>
  <Writer>Alan Page</Writer>
  <absolute_number>9</absolute_number>
  <filename>episodes/290853/5555787.jpg</filename>
  <lastupdated>1461698352</lastupdated>
  <seasonid>651490</seasonid>
  <seriesid>290853</seriesid>
  <thumb_added>2016-04-18 08:22:16</thumb_added>
  <thumb_height>225</thumb_height>
  <thumb_width>400</thumb_width>
</Episode>
<Episode>
  <id>5555788</id>
  <Combined_episodenumber>4</Combined_episodenumber>
  <Combined_season>2</Combined_season>
  <DVD_chapter></DVD_chapter>
  <DVD_discid></DVD_discid>
  <DVD_episodenumber></DVD_episodenumber>
  <DVD_season></DVD_season>
  <Director></Director>
  <EpImgFlag>2</EpImgFlag>
  <EpisodeName>Blood in the Streets</EpisodeName>
  <EpisodeNumber>4</EpisodeNumber>
  <FirstAired>2016-05-01</FirstAired>
  <GuestStars></GuestStars>
  <IMDB_ID></IMDB_ID>
  <Language>en</Language>
  <Overview>The group lets a family in distress board the Abigail; Strand's past begins to come to light; Nick looks for an associate of Strand's.</Overview>
  <ProductionCode></ProductionCode>
  <Rating></Rating>
  <RatingCount>0</RatingCount>
  <SeasonNumber>2</SeasonNumber>
  <Writer></Writer>
  <absolute_number>10</absolute_number>
  <filename>episodes/290853/5555788.jpg</filename>
  <lastupdated>1461599363</lastupdated>
  <seasonid>651490</seasonid>
  <seriesid>290853</seriesid>
  <thumb_added>2016-04-25 08:48:27</thumb_added>
  <thumb_height>225</thumb_height>
  <thumb_width>400</thumb_width>
</Episode>
<Episode>
  <id>5590363</id>
  <Combined_episodenumber>5</Combined_episodenumber>
  <Combined_season>2</Combined_season>
  <DVD_chapter></DVD_chapter>
  <DVD_discid></DVD_discid>
  <DVD_episodenumber></DVD_episodenumber>
  <DVD_season></DVD_season>
  <Director></Director>
  <EpImgFlag></EpImgFlag>
  <EpisodeName>Captive</EpisodeName>
  <EpisodeNumber>5</EpisodeNumber>
  <FirstAired>2016-05-08</FirstAired>
  <GuestStars></GuestStars>
  <IMDB_ID></IMDB_ID>
  <Language>en</Language>
  <Overview>Alicia works toward reuniting with her family; Travis comes across a familiar face; Madison and Nick try to save their family against all odds.</Overview>
  <ProductionCode></ProductionCode>
  <Rating></Rating>
  <RatingCount>0</RatingCount>
  <SeasonNumber>2</SeasonNumber>
  <Writer></Writer>
  <absolute_number></absolute_number>
  <filename></filename>
  <lastupdated>1461357699</lastupdated>
  <seasonid>651490</seasonid>
  <seriesid>290853</seriesid>
  <thumb_added></thumb_added>
  <thumb_height></thumb_height>
  <thumb_width></thumb_width>
</Episode>
<Episode>
  <id>5590364</id>
  <Combined_episodenumber>6</Combined_episodenumber>
  <Combined_season>2</Combined_season>
  <DVD_chapter></DVD_chapter>
  <DVD_discid></DVD_discid>
  <DVD_episodenumber></DVD_episodenumber>
  <DVD_season></DVD_season>
  <Director></Director>
  <EpImgFlag></EpImgFlag>
  <EpisodeName>Sicut Cervus</EpisodeName>
  <EpisodeNumber>6</EpisodeNumber>
  <FirstAired>2016-05-15</FirstAired>
  <GuestStars></GuestStars>
  <IMDB_ID></IMDB_ID>
  <Language>en</Language>
  <Overview>Conflict arises as the Abigail approaches its destination; Chris makes a staggering decision; Nick meets a new maternal figure.</Overview>
  <ProductionCode></ProductionCode>
  <Rating></Rating>
  <RatingCount>0</RatingCount>
  <SeasonNumber>2</SeasonNumber>
  <Writer></Writer>
  <absolute_number></absolute_number>
  <filename></filename>
  <lastupdated>1461357738</lastupdated>
  <seasonid>651490</seasonid>
  <seriesid>290853</seriesid>
  <thumb_added></thumb_added>
  <thumb_height></thumb_height>
  <thumb_width></thumb_width>
</Episode>
<Episode>
  <id>5593116</id>
  <Combined_episodenumber>7</Combined_episodenumber>
  <Combined_season>2</Combined_season>
  <DVD_chapter></DVD_chapter>
  <DVD_discid></DVD_discid>
  <DVD_episodenumber></DVD_episodenumber>
  <DVD_season></DVD_season>
  <Director></Director>
  <EpImgFlag></EpImgFlag>
  <EpisodeName>TBA</EpisodeName>
  <EpisodeNumber>7</EpisodeNumber>
  <FirstAired>2016-05-22</FirstAired>
  <GuestStars></GuestStars>
  <IMDB_ID></IMDB_ID>
  <Language>en</Language>
  <Overview></Overview>
  <ProductionCode></ProductionCode>
  <Rating></Rating>
  <RatingCount>0</RatingCount>
  <SeasonNumber>2</SeasonNumber>
  <Writer></Writer>
  <absolute_number></absolute_number>
  <filename></filename>
  <lastupdated>1461523392</lastupdated>
  <seasonid>651490</seasonid>
  <seriesid>290853</seriesid>
  <thumb_added></thumb_added>
  <thumb_height></thumb_height>
  <thumb_width></thumb_width>
</Episode>
</Data>
